{"expand": "renderedFields,names,schema,operations,editmeta,changelog,versionedRepresentations", "id": "13621317", "self": "https://issues.apache.org/jira/rest/api/2/issue/13621317", "key": "HADOOP-19590", "fields": {"summary": "Encryption tests fail for public buckets ", "description": "When running with SSE-C (and probably other encryption methods?),\u00a0 reading from a public bucket such as `noaa-cors`, tests will fail as objects in the public bucket are no encrypted. Any test reading pre-existing objects should be skipped when setting encryption to anything other than SSE-S3.\u00a0", "reporter": {"self": "https://issues.apache.org/jira/rest/api/2/user?username=ahmar", "name": "ahmar", "key": "JIRAUSER283484", "avatarUrls": {"48x48": "https://issues.apache.org/jira/secure/useravatar?avatarId=34055", "24x24": "https://issues.apache.org/jira/secure/useravatar?size=small&avatarId=34055", "16x16": "https://issues.apache.org/jira/secure/useravatar?size=xsmall&avatarId=34055", "32x32": "https://issues.apache.org/jira/secure/useravatar?size=medium&avatarId=34055"}, "displayName": "Ahmar Suhail", "active": true, "timeZone": "Etc/UTC"}, "comment": {"comments": [], "maxResults": 0, "total": 0, "startAt": 0}, "priority": {"self": "https://issues.apache.org/jira/rest/api/2/priority/3", "iconUrl": "https://issues.apache.org/jira/images/icons/priorities/major.svg", "name": "Major", "id": "3"}, "status": {"self": "https://issues.apache.org/jira/rest/api/2/status/1", "description": "The issue is open and ready for the assignee to start work on it.", "iconUrl": "https://issues.apache.org/jira/images/icons/statuses/open.png", "name": "Open", "id": "1", "statusCategory": {"self": "https://issues.apache.org/jira/rest/api/2/statuscategory/2", "id": 2, "key": "new", "colorName": "blue-gray", "name": "To Do"}}}}