{"expand": "renderedFields,names,schema,operations,editmeta,changelog,versionedRepresentations", "id": "13611636", "self": "https://issues.apache.org/jira/rest/api/2/issue/13611636", "key": "HADOOP-19498", "fields": {"summary": "Fix ByteBuf leaks in TestShuffleChannelHandler", "description": "A lot of ByteBuf leaks are reported when running with JDK23.\r\n\r\nI have not idea why those are not detected with JDK8, 11 or 17. Maybe something about the logging setup ?", "reporter": {"self": "https://issues.apache.org/jira/rest/api/2/user?username=stoty", "name": "stoty", "key": "stoty", "avatarUrls": {"48x48": "https://issues.apache.org/jira/secure/useravatar?ownerId=stoty&avatarId=42544", "24x24": "https://issues.apache.org/jira/secure/useravatar?size=small&ownerId=stoty&avatarId=42544", "16x16": "https://issues.apache.org/jira/secure/useravatar?size=xsmall&ownerId=stoty&avatarId=42544", "32x32": "https://issues.apache.org/jira/secure/useravatar?size=medium&ownerId=stoty&avatarId=42544"}, "displayName": "Istvan Toth", "active": true, "timeZone": "Europe/Budapest"}, "comment": {"comments": [{"self": "https://issues.apache.org/jira/rest/api/2/issue/13611636/comment/17934657", "id": "17934657", "author": {"self": "https://issues.apache.org/jira/rest/api/2/user?username=githubbot", "name": "githubbot", "key": "githubbot", "avatarUrls": {"48x48": "https://issues.apache.org/jira/secure/useravatar?avatarId=10452", "24x24": "https://issues.apache.org/jira/secure/useravatar?size=small&avatarId=10452", "16x16": "https://issues.apache.org/jira/secure/useravatar?size=xsmall&avatarId=10452", "32x32": "https://issues.apache.org/jira/secure/useravatar?size=medium&avatarId=10452"}, "displayName": "ASF GitHub Bot", "active": true, "timeZone": "Etc/UTC"}, "body": "stoty opened a new pull request, #7500:\nURL: https://github.com/apache/hadoop/pull/7500\n\n   ### Description of PR\r\n   \r\n   Fixes ByteBuf leaks in TestShuffleChannelHandler. For some reason the ByteBuf leaks are not detected on older (8,11,17) JVMs, though in retrospect it's quite obvious that the tests don't release ByteBufs as they should.\r\n   \r\n   ### How was this patch tested?\r\n   \r\n   The patch was tested on my JDK23 branch. \r\n   The test probably cannot be run with JDK23 on trunk.\r\n   \r\n   ### For code changes:\r\n   \r\n   - [X] Does the title or this PR starts with the corresponding JIRA issue id (e.g. 'HADOOP-17799. Your PR title ...')?\r\n   - [ ] Object storage: have the integration tests been executed and the endpoint declared according to the connector-specific documentation?\r\n   - [ ] If adding new dependencies to the code, are these dependencies licensed in a way that is compatible for inclusion under [ASF 2.0](http://www.apache.org/legal/resolved.html#category-a)?\r\n   - [ ] If applicable, have you updated the `LICENSE`, `LICENSE-binary`, `NOTICE-binary` files?\r\n   \r\n   \n\n\n", "updateAuthor": {"self": "https://issues.apache.org/jira/rest/api/2/user?username=githubbot", "name": "githubbot", "key": "githubbot", "avatarUrls": {"48x48": "https://issues.apache.org/jira/secure/useravatar?avatarId=10452", "24x24": "https://issues.apache.org/jira/secure/useravatar?size=small&avatarId=10452", "16x16": "https://issues.apache.org/jira/secure/useravatar?size=xsmall&avatarId=10452", "32x32": "https://issues.apache.org/jira/secure/useravatar?size=medium&avatarId=10452"}, "displayName": "ASF GitHub Bot", "active": true, "timeZone": "Etc/UTC"}, "created": "2025-03-12T21:09:54.290+0000", "updated": "2025-03-12T21:09:54.290+0000"}, {"self": "https://issues.apache.org/jira/rest/api/2/issue/13611636/comment/17935014", "id": "17935014", "author": {"self": "https://issues.apache.org/jira/rest/api/2/user?username=githubbot", "name": "githubbot", "key": "githubbot", "avatarUrls": {"48x48": "https://issues.apache.org/jira/secure/useravatar?avatarId=10452", "24x24": "https://issues.apache.org/jira/secure/useravatar?size=small&avatarId=10452", "16x16": "https://issues.apache.org/jira/secure/useravatar?size=xsmall&avatarId=10452", "32x32": "https://issues.apache.org/jira/secure/useravatar?size=medium&avatarId=10452"}, "displayName": "ASF GitHub Bot", "active": true, "timeZone": "Etc/UTC"}, "body": "hadoop-yetus commented on PR #7500:\nURL: https://github.com/apache/hadoop/pull/7500#issuecomment-2719316865\n\n   :confetti_ball: **+1 overall**\r\n   \r\n   \r\n   \r\n   \r\n   \r\n   \r\n   | Vote | Subsystem | Runtime |  Logfile | Comment |\r\n   |:----:|----------:|--------:|:--------:|:-------:|\r\n   | +0 :ok: |  reexec  |   1m  8s |  |  Docker mode activated.  |\r\n   |||| _ Prechecks _ |\r\n   | +1 :green_heart: |  dupname  |   0m  1s |  |  No case conflicting files found.  |\r\n   | +0 :ok: |  codespell  |   0m  0s |  |  codespell was not available.  |\r\n   | +0 :ok: |  detsecrets  |   0m  0s |  |  detect-secrets was not available.  |\r\n   | +1 :green_heart: |  @author  |   0m  0s |  |  The patch does not contain any @author tags.  |\r\n   | +1 :green_heart: |  test4tests  |   0m  0s |  |  The patch appears to include 2 new or modified test files.  |\r\n   |||| _ trunk Compile Tests _ |\r\n   | +1 :green_heart: |  mvninstall  |  35m 21s |  |  trunk passed  |\r\n   | +1 :green_heart: |  compile  |   0m 28s |  |  trunk passed with JDK Ubuntu-11.0.26+4-post-Ubuntu-1ubuntu120.04  |\r\n   | +1 :green_heart: |  compile  |   0m 27s |  |  trunk passed with JDK Private Build-1.8.0_442-8u442-b06~us1-0ubuntu1~20.04-b06  |\r\n   | +1 :green_heart: |  checkstyle  |   0m 28s |  |  trunk passed  |\r\n   | +1 :green_heart: |  mvnsite  |   0m 31s |  |  trunk passed  |\r\n   | +1 :green_heart: |  javadoc  |   0m 33s |  |  trunk passed with JDK Ubuntu-11.0.26+4-post-Ubuntu-1ubuntu120.04  |\r\n   | +1 :green_heart: |  javadoc  |   0m 28s |  |  trunk passed with JDK Private Build-1.8.0_442-8u442-b06~us1-0ubuntu1~20.04-b06  |\r\n   | +1 :green_heart: |  spotbugs  |   0m 49s |  |  trunk passed  |\r\n   | +1 :green_heart: |  shadedclient  |  34m 11s |  |  branch has no errors when building and testing our client artifacts.  |\r\n   |||| _ Patch Compile Tests _ |\r\n   | +1 :green_heart: |  mvninstall  |   0m 18s |  |  the patch passed  |\r\n   | +1 :green_heart: |  compile  |   0m 18s |  |  the patch passed with JDK Ubuntu-11.0.26+4-post-Ubuntu-1ubuntu120.04  |\r\n   | +1 :green_heart: |  javac  |   0m 18s |  |  the patch passed  |\r\n   | +1 :green_heart: |  compile  |   0m 18s |  |  the patch passed with JDK Private Build-1.8.0_442-8u442-b06~us1-0ubuntu1~20.04-b06  |\r\n   | +1 :green_heart: |  javac  |   0m 18s |  |  the patch passed  |\r\n   | +1 :green_heart: |  blanks  |   0m  0s |  |  The patch has no blanks issues.  |\r\n   | -0 :warning: |  checkstyle  |   0m 14s | [/results-checkstyle-hadoop-mapreduce-project_hadoop-mapreduce-client_hadoop-mapreduce-client-shuffle.txt](https://ci-hadoop.apache.org/job/hadoop-multibranch/job/PR-7500/1/artifact/out/results-checkstyle-hadoop-mapreduce-project_hadoop-mapreduce-client_hadoop-mapreduce-client-shuffle.txt) |  hadoop-mapreduce-project/hadoop-mapreduce-client/hadoop-mapreduce-client-shuffle: The patch generated 2 new + 0 unchanged - 0 fixed = 2 total (was 0)  |\r\n   | +1 :green_heart: |  mvnsite  |   0m 20s |  |  the patch passed  |\r\n   | +1 :green_heart: |  javadoc  |   0m 19s |  |  the patch passed with JDK Ubuntu-11.0.26+4-post-Ubuntu-1ubuntu120.04  |\r\n   | +1 :green_heart: |  javadoc  |   0m 18s |  |  the patch passed with JDK Private Build-1.8.0_442-8u442-b06~us1-0ubuntu1~20.04-b06  |\r\n   | +1 :green_heart: |  spotbugs  |   0m 43s |  |  the patch passed  |\r\n   | +1 :green_heart: |  shadedclient  |  33m 59s |  |  patch has no errors when building and testing our client artifacts.  |\r\n   |||| _ Other Tests _ |\r\n   | +1 :green_heart: |  unit  |   0m 59s |  |  hadoop-mapreduce-client-shuffle in the patch passed.  |\r\n   | +1 :green_heart: |  asflicense  |   0m 36s |  |  The patch does not generate ASF License warnings.  |\r\n   |  |   | 114m 47s |  |  |\r\n   \r\n   \r\n   | Subsystem | Report/Notes |\r\n   |----------:|:-------------|\r\n   | Docker | ClientAPI=1.48 ServerAPI=1.48 base: https://ci-hadoop.apache.org/job/hadoop-multibranch/job/PR-7500/1/artifact/out/Dockerfile |\r\n   | GITHUB PR | https://github.com/apache/hadoop/pull/7500 |\r\n   | Optional Tests | dupname asflicense compile javac javadoc mvninstall mvnsite unit shadedclient spotbugs checkstyle codespell detsecrets |\r\n   | uname | Linux 2b91e841e013 5.15.0-130-generic #140-Ubuntu SMP Wed Dec 18 17:59:53 UTC 2024 x86_64 x86_64 x86_64 GNU/Linux |\r\n   | Build tool | maven |\r\n   | Personality | dev-support/bin/hadoop.sh |\r\n   | git revision | trunk / e252de3bcf40124251e60f4dc777752311fab9b0 |\r\n   | Default Java | Private Build-1.8.0_442-8u442-b06~us1-0ubuntu1~20.04-b06 |\r\n   | Multi-JDK versions | /usr/lib/jvm/java-11-openjdk-amd64:Ubuntu-11.0.26+4-post-Ubuntu-1ubuntu120.04 /usr/lib/jvm/java-8-openjdk-amd64:Private Build-1.8.0_442-8u442-b06~us1-0ubuntu1~20.04-b06 |\r\n   |  Test Results | https://ci-hadoop.apache.org/job/hadoop-multibranch/job/PR-7500/1/testReport/ |\r\n   | Max. process+thread count | 544 (vs. ulimit of 5500) |\r\n   | modules | C: hadoop-mapreduce-project/hadoop-mapreduce-client/hadoop-mapreduce-client-shuffle U: hadoop-mapreduce-project/hadoop-mapreduce-client/hadoop-mapreduce-client-shuffle |\r\n   | Console output | https://ci-hadoop.apache.org/job/hadoop-multibranch/job/PR-7500/1/console |\r\n   | versions | git=2.25.1 maven=3.6.3 spotbugs=4.2.2 |\r\n   | Powered by | Apache Yetus 0.14.0 https://yetus.apache.org |\r\n   \r\n   \r\n   This message was automatically generated.\r\n   \r\n   \n\n\n", "updateAuthor": {"self": "https://issues.apache.org/jira/rest/api/2/user?username=githubbot", "name": "githubbot", "key": "githubbot", "avatarUrls": {"48x48": "https://issues.apache.org/jira/secure/useravatar?avatarId=10452", "24x24": "https://issues.apache.org/jira/secure/useravatar?size=small&avatarId=10452", "16x16": "https://issues.apache.org/jira/secure/useravatar?size=xsmall&avatarId=10452", "32x32": "https://issues.apache.org/jira/secure/useravatar?size=medium&avatarId=10452"}, "displayName": "ASF GitHub Bot", "active": true, "timeZone": "Etc/UTC"}, "created": "2025-03-12T23:05:57.459+0000", "updated": "2025-03-12T23:05:57.459+0000"}, {"self": "https://issues.apache.org/jira/rest/api/2/issue/13611636/comment/17935023", "id": "17935023", "author": {"self": "https://issues.apache.org/jira/rest/api/2/user?username=githubbot", "name": "githubbot", "key": "githubbot", "avatarUrls": {"48x48": "https://issues.apache.org/jira/secure/useravatar?avatarId=10452", "24x24": "https://issues.apache.org/jira/secure/useravatar?size=small&avatarId=10452", "16x16": "https://issues.apache.org/jira/secure/useravatar?size=xsmall&avatarId=10452", "32x32": "https://issues.apache.org/jira/secure/useravatar?size=medium&avatarId=10452"}, "displayName": "ASF GitHub Bot", "active": true, "timeZone": "Etc/UTC"}, "body": "slfan1989 commented on PR #7500:\nURL: https://github.com/apache/hadoop/pull/7500#issuecomment-2719387042\n\n   @stoty Overall it looks good. Can we fix the checkstyle issue?\n\n\n", "updateAuthor": {"self": "https://issues.apache.org/jira/rest/api/2/user?username=githubbot", "name": "githubbot", "key": "githubbot", "avatarUrls": {"48x48": "https://issues.apache.org/jira/secure/useravatar?avatarId=10452", "24x24": "https://issues.apache.org/jira/secure/useravatar?size=small&avatarId=10452", "16x16": "https://issues.apache.org/jira/secure/useravatar?size=xsmall&avatarId=10452", "32x32": "https://issues.apache.org/jira/secure/useravatar?size=medium&avatarId=10452"}, "displayName": "ASF GitHub Bot", "active": true, "timeZone": "Etc/UTC"}, "created": "2025-03-13T00:04:09.113+0000", "updated": "2025-03-13T00:04:09.113+0000"}, {"self": "https://issues.apache.org/jira/rest/api/2/issue/13611636/comment/17935064", "id": "17935064", "author": {"self": "https://issues.apache.org/jira/rest/api/2/user?username=githubbot", "name": "githubbot", "key": "githubbot", "avatarUrls": {"48x48": "https://issues.apache.org/jira/secure/useravatar?avatarId=10452", "24x24": "https://issues.apache.org/jira/secure/useravatar?size=small&avatarId=10452", "16x16": "https://issues.apache.org/jira/secure/useravatar?size=xsmall&avatarId=10452", "32x32": "https://issues.apache.org/jira/secure/useravatar?size=medium&avatarId=10452"}, "displayName": "ASF GitHub Bot", "active": true, "timeZone": "Etc/UTC"}, "body": "stoty commented on PR #7500:\nURL: https://github.com/apache/hadoop/pull/7500#issuecomment-2720019198\n\n   Thank you @slfan1989 .\r\n   I've hepfully fixed the checkstyle issues.\r\n   I've also moved the release calls to right after the last access of the potential ByteBuf variable in most cases.\n\n\n", "updateAuthor": {"self": "https://issues.apache.org/jira/rest/api/2/user?username=githubbot", "name": "githubbot", "key": "githubbot", "avatarUrls": {"48x48": "https://issues.apache.org/jira/secure/useravatar?avatarId=10452", "24x24": "https://issues.apache.org/jira/secure/useravatar?size=small&avatarId=10452", "16x16": "https://issues.apache.org/jira/secure/useravatar?size=xsmall&avatarId=10452", "32x32": "https://issues.apache.org/jira/secure/useravatar?size=medium&avatarId=10452"}, "displayName": "ASF GitHub Bot", "active": true, "timeZone": "Etc/UTC"}, "created": "2025-03-13T05:22:47.743+0000", "updated": "2025-03-13T05:22:47.743+0000"}, {"self": "https://issues.apache.org/jira/rest/api/2/issue/13611636/comment/17935076", "id": "17935076", "author": {"self": "https://issues.apache.org/jira/rest/api/2/user?username=githubbot", "name": "githubbot", "key": "githubbot", "avatarUrls": {"48x48": "https://issues.apache.org/jira/secure/useravatar?avatarId=10452", "24x24": "https://issues.apache.org/jira/secure/useravatar?size=small&avatarId=10452", "16x16": "https://issues.apache.org/jira/secure/useravatar?size=xsmall&avatarId=10452", "32x32": "https://issues.apache.org/jira/secure/useravatar?size=medium&avatarId=10452"}, "displayName": "ASF GitHub Bot", "active": true, "timeZone": "Etc/UTC"}, "body": "hadoop-yetus commented on PR #7500:\nURL: https://github.com/apache/hadoop/pull/7500#issuecomment-2720190154\n\n   :confetti_ball: **+1 overall**\r\n   \r\n   \r\n   \r\n   \r\n   \r\n   \r\n   | Vote | Subsystem | Runtime |  Logfile | Comment |\r\n   |:----:|----------:|--------:|:--------:|:-------:|\r\n   | +0 :ok: |  reexec  |   0m 56s |  |  Docker mode activated.  |\r\n   |||| _ Prechecks _ |\r\n   | +1 :green_heart: |  dupname  |   0m  0s |  |  No case conflicting files found.  |\r\n   | +0 :ok: |  codespell  |   0m  0s |  |  codespell was not available.  |\r\n   | +0 :ok: |  detsecrets  |   0m  0s |  |  detect-secrets was not available.  |\r\n   | +1 :green_heart: |  @author  |   0m  0s |  |  The patch does not contain any @author tags.  |\r\n   | +1 :green_heart: |  test4tests  |   0m  0s |  |  The patch appears to include 2 new or modified test files.  |\r\n   |||| _ trunk Compile Tests _ |\r\n   | +1 :green_heart: |  mvninstall  |  37m 20s |  |  trunk passed  |\r\n   | +1 :green_heart: |  compile  |   0m 28s |  |  trunk passed with JDK Ubuntu-11.0.26+4-post-Ubuntu-1ubuntu120.04  |\r\n   | +1 :green_heart: |  compile  |   0m 26s |  |  trunk passed with JDK Private Build-1.8.0_442-8u442-b06~us1-0ubuntu1~20.04-b06  |\r\n   | +1 :green_heart: |  checkstyle  |   0m 28s |  |  trunk passed  |\r\n   | +1 :green_heart: |  mvnsite  |   0m 31s |  |  trunk passed  |\r\n   | +1 :green_heart: |  javadoc  |   0m 33s |  |  trunk passed with JDK Ubuntu-11.0.26+4-post-Ubuntu-1ubuntu120.04  |\r\n   | +1 :green_heart: |  javadoc  |   0m 28s |  |  trunk passed with JDK Private Build-1.8.0_442-8u442-b06~us1-0ubuntu1~20.04-b06  |\r\n   | +1 :green_heart: |  spotbugs  |   0m 48s |  |  trunk passed  |\r\n   | +1 :green_heart: |  shadedclient  |  34m  3s |  |  branch has no errors when building and testing our client artifacts.  |\r\n   |||| _ Patch Compile Tests _ |\r\n   | +1 :green_heart: |  mvninstall  |   0m 19s |  |  the patch passed  |\r\n   | +1 :green_heart: |  compile  |   0m 19s |  |  the patch passed with JDK Ubuntu-11.0.26+4-post-Ubuntu-1ubuntu120.04  |\r\n   | +1 :green_heart: |  javac  |   0m 19s |  |  the patch passed  |\r\n   | +1 :green_heart: |  compile  |   0m 18s |  |  the patch passed with JDK Private Build-1.8.0_442-8u442-b06~us1-0ubuntu1~20.04-b06  |\r\n   | +1 :green_heart: |  javac  |   0m 18s |  |  the patch passed  |\r\n   | +1 :green_heart: |  blanks  |   0m  0s |  |  The patch has no blanks issues.  |\r\n   | +1 :green_heart: |  checkstyle  |   0m 14s |  |  the patch passed  |\r\n   | +1 :green_heart: |  mvnsite  |   0m 21s |  |  the patch passed  |\r\n   | +1 :green_heart: |  javadoc  |   0m 20s |  |  the patch passed with JDK Ubuntu-11.0.26+4-post-Ubuntu-1ubuntu120.04  |\r\n   | +1 :green_heart: |  javadoc  |   0m 19s |  |  the patch passed with JDK Private Build-1.8.0_442-8u442-b06~us1-0ubuntu1~20.04-b06  |\r\n   | +1 :green_heart: |  spotbugs  |   0m 43s |  |  the patch passed  |\r\n   | +1 :green_heart: |  shadedclient  |  33m 47s |  |  patch has no errors when building and testing our client artifacts.  |\r\n   |||| _ Other Tests _ |\r\n   | +1 :green_heart: |  unit  |   1m  2s |  |  hadoop-mapreduce-client-shuffle in the patch passed.  |\r\n   | +1 :green_heart: |  asflicense  |   0m 37s |  |  The patch does not generate ASF License warnings.  |\r\n   |  |   | 116m  9s |  |  |\r\n   \r\n   \r\n   | Subsystem | Report/Notes |\r\n   |----------:|:-------------|\r\n   | Docker | ClientAPI=1.48 ServerAPI=1.48 base: https://ci-hadoop.apache.org/job/hadoop-multibranch/job/PR-7500/2/artifact/out/Dockerfile |\r\n   | GITHUB PR | https://github.com/apache/hadoop/pull/7500 |\r\n   | Optional Tests | dupname asflicense compile javac javadoc mvninstall mvnsite unit shadedclient spotbugs checkstyle codespell detsecrets |\r\n   | uname | Linux d36abdd245f8 5.15.0-130-generic #140-Ubuntu SMP Wed Dec 18 17:59:53 UTC 2024 x86_64 x86_64 x86_64 GNU/Linux |\r\n   | Build tool | maven |\r\n   | Personality | dev-support/bin/hadoop.sh |\r\n   | git revision | trunk / 7384215ac9bcfddfa959b11a5828343983c83b0c |\r\n   | Default Java | Private Build-1.8.0_442-8u442-b06~us1-0ubuntu1~20.04-b06 |\r\n   | Multi-JDK versions | /usr/lib/jvm/java-11-openjdk-amd64:Ubuntu-11.0.26+4-post-Ubuntu-1ubuntu120.04 /usr/lib/jvm/java-8-openjdk-amd64:Private Build-1.8.0_442-8u442-b06~us1-0ubuntu1~20.04-b06 |\r\n   |  Test Results | https://ci-hadoop.apache.org/job/hadoop-multibranch/job/PR-7500/2/testReport/ |\r\n   | Max. process+thread count | 548 (vs. ulimit of 5500) |\r\n   | modules | C: hadoop-mapreduce-project/hadoop-mapreduce-client/hadoop-mapreduce-client-shuffle U: hadoop-mapreduce-project/hadoop-mapreduce-client/hadoop-mapreduce-client-shuffle |\r\n   | Console output | https://ci-hadoop.apache.org/job/hadoop-multibranch/job/PR-7500/2/console |\r\n   | versions | git=2.25.1 maven=3.6.3 spotbugs=4.2.2 |\r\n   | Powered by | Apache Yetus 0.14.0 https://yetus.apache.org |\r\n   \r\n   \r\n   This message was automatically generated.\r\n   \r\n   \n\n\n", "updateAuthor": {"self": "https://issues.apache.org/jira/rest/api/2/user?username=githubbot", "name": "githubbot", "key": "githubbot", "avatarUrls": {"48x48": "https://issues.apache.org/jira/secure/useravatar?avatarId=10452", "24x24": "https://issues.apache.org/jira/secure/useravatar?size=small&avatarId=10452", "16x16": "https://issues.apache.org/jira/secure/useravatar?size=xsmall&avatarId=10452", "32x32": "https://issues.apache.org/jira/secure/useravatar?size=medium&avatarId=10452"}, "displayName": "ASF GitHub Bot", "active": true, "timeZone": "Etc/UTC"}, "created": "2025-03-13T07:10:19.828+0000", "updated": "2025-03-13T07:10:19.828+0000"}, {"self": "https://issues.apache.org/jira/rest/api/2/issue/13611636/comment/17935383", "id": "17935383", "author": {"self": "https://issues.apache.org/jira/rest/api/2/user?username=githubbot", "name": "githubbot", "key": "githubbot", "avatarUrls": {"48x48": "https://issues.apache.org/jira/secure/useravatar?avatarId=10452", "24x24": "https://issues.apache.org/jira/secure/useravatar?size=small&avatarId=10452", "16x16": "https://issues.apache.org/jira/secure/useravatar?size=xsmall&avatarId=10452", "32x32": "https://issues.apache.org/jira/secure/useravatar?size=medium&avatarId=10452"}, "displayName": "ASF GitHub Bot", "active": true, "timeZone": "Etc/UTC"}, "body": "slfan1989 commented on PR #7500:\nURL: https://github.com/apache/hadoop/pull/7500#issuecomment-2723029896\n\n   @stoty Thanks for the contribution! Merged into trunk.\n\n\n", "updateAuthor": {"self": "https://issues.apache.org/jira/rest/api/2/user?username=githubbot", "name": "githubbot", "key": "githubbot", "avatarUrls": {"48x48": "https://issues.apache.org/jira/secure/useravatar?avatarId=10452", "24x24": "https://issues.apache.org/jira/secure/useravatar?size=small&avatarId=10452", "16x16": "https://issues.apache.org/jira/secure/useravatar?size=xsmall&avatarId=10452", "32x32": "https://issues.apache.org/jira/secure/useravatar?size=medium&avatarId=10452"}, "displayName": "ASF GitHub Bot", "active": true, "timeZone": "Etc/UTC"}, "created": "2025-03-14T00:47:09.103+0000", "updated": "2025-03-14T00:47:09.103+0000"}, {"self": "https://issues.apache.org/jira/rest/api/2/issue/13611636/comment/17935384", "id": "17935384", "author": {"self": "https://issues.apache.org/jira/rest/api/2/user?username=githubbot", "name": "githubbot", "key": "githubbot", "avatarUrls": {"48x48": "https://issues.apache.org/jira/secure/useravatar?avatarId=10452", "24x24": "https://issues.apache.org/jira/secure/useravatar?size=small&avatarId=10452", "16x16": "https://issues.apache.org/jira/secure/useravatar?size=xsmall&avatarId=10452", "32x32": "https://issues.apache.org/jira/secure/useravatar?size=medium&avatarId=10452"}, "displayName": "ASF GitHub Bot", "active": true, "timeZone": "Etc/UTC"}, "body": "slfan1989 commented on PR #7500:\nURL: https://github.com/apache/hadoop/pull/7500#issuecomment-2723042784\n\n   @stoty I've identified a minor issue, which should be related to MapReduce. I will create a MapReduce Jira to associate with it.\n\n\n", "updateAuthor": {"self": "https://issues.apache.org/jira/rest/api/2/user?username=githubbot", "name": "githubbot", "key": "githubbot", "avatarUrls": {"48x48": "https://issues.apache.org/jira/secure/useravatar?avatarId=10452", "24x24": "https://issues.apache.org/jira/secure/useravatar?size=small&avatarId=10452", "16x16": "https://issues.apache.org/jira/secure/useravatar?size=xsmall&avatarId=10452", "32x32": "https://issues.apache.org/jira/secure/useravatar?size=medium&avatarId=10452"}, "displayName": "ASF GitHub Bot", "active": true, "timeZone": "Etc/UTC"}, "created": "2025-03-14T00:55:02.878+0000", "updated": "2025-03-14T00:55:02.878+0000"}], "maxResults": 7, "total": 7, "startAt": 0}, "priority": {"self": "https://issues.apache.org/jira/rest/api/2/priority/3", "iconUrl": "https://issues.apache.org/jira/images/icons/priorities/major.svg", "name": "Major", "id": "3"}, "status": {"self": "https://issues.apache.org/jira/rest/api/2/status/5", "description": "A resolution has been taken, and it is awaiting verification by reporter. From here issues are either reopened, or are closed.", "iconUrl": "https://issues.apache.org/jira/images/icons/statuses/resolved.png", "name": "Resolved", "id": "5", "statusCategory": {"self": "https://issues.apache.org/jira/rest/api/2/statuscategory/3", "id": 3, "key": "done", "colorName": "green", "name": "Done"}}}}